{
  "version": "1.9.2",
  "date": 1747750494304,
  "preferences": {
    "automaticMode": {
      "active": true,
      "newTab": "created"
    },
    "notifications": false,
    "container": {
      "namePrefix": "tmp",
      "color": "toolbar",
      "colorRandom": false,
      "colorRandomExcluded": [],
      "icon": "circle",
      "iconRandom": false,
      "iconRandomExcluded": [],
      "numberMode": "reuse",
      "removal": 900000
    },
    "iconColor": "default",
    "isolation": {
      "reactivateDelay": 0,
      "global": {
        "navigation": {
          "action": "notsamedomain"
        },
        "mouseClick": {
          "middle": {
            "action": "never",
            "container": "default"
          },
          "ctrlleft": {
            "action": "never",
            "container": "default"
          },
          "left": {
            "action": "never",
            "container": "default"
          }
        },
        "excluded": {
          "login.microsoftonline.com": {},
          "secure.kps-payment.de": {},
          "*.login.microsoftonline.com": {},
          "id.bund.de": {},
          "threedssvc.pay1.de": {}
        },
        "excludedContainers": []
      },
      "domain": [
        {
          "pattern": "login.microsoftonline.com",
          "always": {
            "action": "disabled",
            "allowedInPermanent": false,
            "allowedInTemporary": false
          },
          "navigation": {
            "action": "never"
          },
          "mouseClick": {
            "middle": {
              "action": "global"
            },
            "ctrlleft": {
              "action": "global"
            },
            "left": {
              "action": "global"
            }
          },
          "excluded": {}
        },
        {
          "pattern": "secure.kps-payment.de",
          "always": {
            "action": "disabled",
            "allowedInPermanent": false,
            "allowedInTemporary": false
          },
          "navigation": {
            "action": "never"
          },
          "mouseClick": {
            "middle": {
              "action": "global"
            },
            "ctrlleft": {
              "action": "global"
            },
            "left": {
              "action": "global"
            }
          },
          "excluded": {}
        },
        {
          "pattern": "*.login.microsoftonline.com",
          "always": {
            "action": "disabled",
            "allowedInPermanent": false,
            "allowedInTemporary": false
          },
          "navigation": {
            "action": "never"
          },
          "mouseClick": {
            "middle": {
              "action": "global"
            },
            "ctrlleft": {
              "action": "global"
            },
            "left": {
              "action": "global"
            }
          },
          "excluded": {}
        },
        {
          "pattern": "id.bund.de",
          "always": {
            "action": "disabled",
            "allowedInPermanent": false,
            "allowedInTemporary": false
          },
          "navigation": {
            "action": "never"
          },
          "mouseClick": {
            "middle": {
              "action": "global"
            },
            "ctrlleft": {
              "action": "global"
            },
            "left": {
              "action": "global"
            }
          },
          "excluded": {}
        },
        {
          "pattern": "/^moz-extension:\\/\\/[a-z0-9-]+\\/delayed\\.html.*/",
          "always": {
            "action": "disabled",
            "allowedInPermanent": false,
            "allowedInTemporary": false
          },
          "navigation": {
            "action": "never"
          },
          "mouseClick": {
            "middle": {
              "action": "global"
            },
            "ctrlleft": {
              "action": "global"
            },
            "left": {
              "action": "global"
            }
          },
          "excluded": {}
        },
        {
          "pattern": "threedssvc.pay1.de",
          "always": {
            "action": "disabled",
            "allowedInPermanent": false,
            "allowedInTemporary": false
          },
          "navigation": {
            "action": "never"
          },
          "mouseClick": {
            "middle": {
              "action": "global"
            },
            "ctrlleft": {
              "action": "global"
            },
            "left": {
              "action": "global"
            }
          },
          "excluded": {}
        }
      ],
      "mac": {
        "action": "enabled"
      }
    },
    "browserActionPopup": false,
    "pageAction": false,
    "contextMenu": false,
    "contextMenuBookmarks": false,
    "keyboardShortcuts": {
      "AltC": false,
      "AltP": true,
      "AltN": false,
      "AltShiftC": false,
      "AltX": false,
      "AltO": false,
      "AltI": false
    },
    "replaceTabs": false,
    "closeRedirectorTabs": {
      "active": true,
      "delay": 2000,
      "domains": [
        "t.co",
        "outgoing.prod.mozaws.net",
        "slack-redir.net"
      ]
    },
    "ignoreRequests": [
      "getpocket.com",
      "addons.mozilla.org",
      "5b5e5f00-cdba-421c-b4ea-ff77c9132c48"
    ],
    "cookies": {
      "domain": {
        "*.youtube.com": [
          {
            "domain": ".youtube.com",
            "expirationDate": "",
            "firstPartyDomain": "",
            "httpOnly": "",
            "name": "PREF",
            "path": "/",
            "sameSite": "",
            "secure": "true",
            "url": "https://www.youtube.com/",
            "value": "tz=Europe.Berlin&f4=4000000&f7=100&f5=30000&f6=400"
          },
          {
            "domain": ".youtube.com",
            "expirationDate": "",
            "firstPartyDomain": "",
            "httpOnly": "",
            "name": "wide",
            "path": "/",
            "sameSite": "no_restriction",
            "secure": "false",
            "url": "https://www.youtube.com/",
            "value": "1"
          },
          {
            "domain": ".youtube.com",
            "expirationDate": "",
            "firstPartyDomain": "",
            "httpOnly": "false",
            "name": "SOCS",
            "path": "/",
            "sameSite": "lax",
            "secure": "",
            "url": "https://www.youtube.com/",
            "value": "CAESEwgDEgk3NDA5ODczMTEaAmVuIAEaBgiAk6K_Bg"
          }
        ],
        "*.woki.de": [
          {
            "domain": "www.woki.de",
            "expirationDate": "",
            "firstPartyDomain": "",
            "httpOnly": "false",
            "name": "klaro",
            "path": "/",
            "sameSite": "lax",
            "secure": "false",
            "url": "https://www.woki.de/",
            "value": "%7B%22cpConfig%22%3Atrue%2C%22basicCookie%22%3Atrue%2C%22cpIt%22%3Atrue%2C%22scrollContent%22%3Atrue%2C%22klaro%22%3Atrue%2C%22youtube%22%3Afalse%2C%22googleMaps%22%3Afalse%2C%22googleRecaptcha%22%3Afalse%2C%22googleAnalytics%22%3Afalse%7D"
          }
        ]
      }
    },
    "scripts": {
      "active": true,
      "domain": {
        "www.kraftfuttermischwerk.de": [
          {
            "code": "localStorage.setItem('jetpack_post_subscribe_modal_dismissed', Date.now().toString());",
            "runAt": "document_start"
          }
        ]
      }
    },
    "deletesHistory": {
      "active": false,
      "automaticMode": "never",
      "contextMenu": false,
      "contextMenuBookmarks": false,
      "containerAlwaysPerDomain": "never",
      "containerIsolation": "never",
      "containerRemoval": 0,
      "containerMouseClicks": "never",
      "statistics": false
    },
    "statistics": false,
    "ui": {
      "expandPreferences": false,
      "popupDefaultTab": "isolation-global"
    }
  }
}
